django_filters/__init__.py
django_filters/compat.py
django_filters/conf.py
django_filters/constants.py
django_filters/exceptions.py
django_filters/fields.py
django_filters/filters.py
django_filters/filterset.py
django_filters/utils.py
django_filters/views.py
django_filters/widgets.py
django_filters/locale/ar/LC_MESSAGES/django.mo
django_filters/locale/ar/LC_MESSAGES/django.po
django_filters/locale/be/LC_MESSAGES/django.mo
django_filters/locale/be/LC_MESSAGES/django.po
django_filters/locale/bg/LC_MESSAGES/django.mo
django_filters/locale/bg/LC_MESSAGES/django.po
django_filters/locale/cs/LC_MESSAGES/django.mo
django_filters/locale/cs/LC_MESSAGES/django.po
django_filters/locale/da/LC_MESSAGES/django.mo
django_filters/locale/da/LC_MESSAGES/django.po
django_filters/locale/de/LC_MESSAGES/django.mo
django_filters/locale/de/LC_MESSAGES/django.po
django_filters/locale/el/LC_MESSAGES/django.mo
django_filters/locale/el/LC_MESSAGES/django.po
django_filters/locale/es/LC_MESSAGES/django.mo
django_filters/locale/es/LC_MESSAGES/django.po
django_filters/locale/es_AR/LC_MESSAGES/django.mo
django_filters/locale/es_AR/LC_MESSAGES/django.po
django_filters/locale/fa/LC_MESSAGES/django.mo
django_filters/locale/fa/LC_MESSAGES/django.po
django_filters/locale/fi/LC_MESSAGES/django.po
django_filters/locale/fr/LC_MESSAGES/django.mo
django_filters/locale/fr/LC_MESSAGES/django.po
django_filters/locale/it/LC_MESSAGES/django.mo
django_filters/locale/it/LC_MESSAGES/django.po
django_filters/locale/nl/LC_MESSAGES/django.po
django_filters/locale/pl/LC_MESSAGES/django.mo
django_filters/locale/pl/LC_MESSAGES/django.po
django_filters/locale/pt_BR/LC_MESSAGES/django.mo
django_filters/locale/pt_BR/LC_MESSAGES/django.po
django_filters/locale/ro/LC_MESSAGES/django.po
django_filters/locale/ru/LC_MESSAGES/django.mo
django_filters/locale/ru/LC_MESSAGES/django.po
django_filters/locale/sk/LC_MESSAGES/django.mo
django_filters/locale/sk/LC_MESSAGES/django.po
django_filters/locale/uk/LC_MESSAGES/django.mo
django_filter-23.2.dist-info/LICENSE
django_filter-23.2.dist-info/METADATA
django_filter-23.2.dist-info/WHEEL
django_filter-23.2.dist-info/top_level.txt
django_filter-23.2.dist-info/RECORD
