Metadata-Version: 2.1
Name: django-filter
Version: 23.2
Summary: Django-filter is a reusable Django application for allowing users to filter querysets dynamically.
Home-page: https://github.com/carltongibson/django-filter/tree/main
Author: Alex Gaynor
Author-email: alex.gaynor@gmail.com
Maintainer: Carlton Gibson
Maintainer-email: carlton.gibson@noumenal.es
License: BSD
Project-URL: Documentation, https://django-filter.readthedocs.io/en/main/
Project-URL: Changelog, https://github.com/carltongibson/django-filter/blob/main/CHANGES.rst
Project-URL: Bug Tracker, https://github.com/carltongibson/django-filter/issues
Project-URL: Source Code, https://github.com/carltongibson/django-filter
Classifier: Development Status :: 5 - Production/Stable
Classifier: Environment :: Web Environment
Classifier: Intended Audience :: Developers
Classifier: License :: OSI Approved :: BSD License
Classifier: Operating System :: OS Independent
Classifier: Framework :: Django
Classifier: Framework :: Django :: 3.2
Classifier: Framework :: Django :: 4.0
Classifier: Framework :: Django :: 4.1
Classifier: Framework :: Django :: 4.2
Classifier: Programming Language :: Python
Classifier: Programming Language :: Python :: 3
Classifier: Programming Language :: Python :: 3.7
Classifier: Programming Language :: Python :: 3.8
Classifier: Programming Language :: Python :: 3.9
Classifier: Programming Language :: Python :: 3.10
Classifier: Programming Language :: Python :: 3.11
Requires-Python: >=3.7
License-File: LICENSE
